ape_notebook/__init__.py
ape_notebook/_cli.py
ape_notebook/py.typed
ape_notebook/version.py
ape_notebook-0.7.0.dist-info/LICENSE
ape_notebook-0.7.0.dist-info/METADATA
ape_notebook-0.7.0.dist-info/WHEEL
ape_notebook-0.7.0.dist-info/entry_points.txt
ape_notebook-0.7.0.dist-info/top_level.txt
ape_notebook-0.7.0.dist-info/RECORD
